{"cameraMode":{"drawMode":0,"name":"Shaded","section":"Shading Mode"},"sceneLighting":true,"audioPlay":false,"sceneViewState":{"m_AlwaysRefresh":false,"showFog":true,"showSkybox":true,"showFlares":true,"showImageEffects":true,"showParticleSystems":true,"showVisualEffectGraphs":true,"m_FxEnabled":true},"in2DMode":false,"pivot":{"x":16.899003982543947,"y":0.753179669380188,"z":0.0},"rotation":{"x":-0.002746937097981572,"y":0.9747298359870911,"z":0.011979843489825726,"w":0.22309550642967225},"size":3.8089728355407717,"orthographic":true}